odoo/addons/cms_toolbar/CHANGES.rst
odoo/addons/cms_toolbar/README.rst
odoo/addons/cms_toolbar/__init__.py
odoo/addons/cms_toolbar/__manifest__.py
odoo/addons/cms_toolbar/i18n/cms_toolbar.pot
odoo/addons/cms_toolbar/images/toolbar_preview.png
odoo/addons/cms_toolbar/models/__init__.py
odoo/addons/cms_toolbar/models/website_mixin.py
odoo/addons/cms_toolbar/static/src/js/publish.js
odoo/addons/cms_toolbar/static/src/js/tooltips.js
odoo/addons/cms_toolbar/static/src/less/toolbar.less
odoo/addons/cms_toolbar/templates/assets.xml
odoo/addons/cms_toolbar/templates/toolbar.xml
odoo/addons/cms_toolbar/tests/__init__.py
odoo/addons/cms_toolbar/tests/fake_models.py
odoo/addons/cms_toolbar/tests/test_rendering.py
odoo11_addon_cms_toolbar-11.0.1.1.1.dist-info/METADATA
odoo11_addon_cms_toolbar-11.0.1.1.1.dist-info/RECORD
odoo11_addon_cms_toolbar-11.0.1.1.1.dist-info/WHEEL
odoo11_addon_cms_toolbar-11.0.1.1.1.dist-info/top_level.txt
